speac/__init__.py
speac/chopin_33_3.py
speac/chopin_63_2.py
speac/chopin_67_4.py
speac/new_form.py
speac/pattern_match.py
speac/speac.py
speac/speac_analysis.py
speac/speac_settings.py
speac/top_level.py
speac-1.0.14.dist-info/LICENSE.txt
speac-1.0.14.dist-info/METADATA
speac-1.0.14.dist-info/WHEEL
speac-1.0.14.dist-info/top_level.txt
speac-1.0.14.dist-info/RECORD
