Metadata-Version: 2.1
Name: speac
Version: 1.0.14
Summary: David Cope's SPEAC-analysis Python library
Home-page: https://github.com/GolzitskyNikolay/SPEAC-analysis/
Author: GlazNik
Author-email: golzitskij.ns@edu.spbstu.ru
License: UNKNOWN
Keywords: SPEAC David Cope
Platform: UNKNOWN
Requires-Python: >=3.0
License-File: LICENSE.txt
